courses/__init__.py
courses/admin.py
courses/apps.py
courses/urls.py
courses/views.py
courses/static/css/courses/mentor_ds.css
courses/templates/courses/_common.html
courses/templates/courses/mentor_ds.html
courses/templates/courses_details/details.html
courses/templatetags/__init__.py
courses/templatetags/courses_tags.py
events/__init__.py
events/admin.py
events/apps.py
events/static/css/events/mentor_ds.css
events/templates/events/_common.html
events/templates/events/mentor_ds.html
events/templatetags/__init__.py
events/templatetags/events_tags.py
features/__init__.py
features/admin.py
features/apps.py
features/static/css/features/mentor_ds.css
features/templates/features/_common.html
features/templates/features/medilab_ds.html
features/templates/features/mentor_ds.html
features/templatetags/__init__.py
features/templatetags/features_tags.py
pricing/__init__.py
pricing/admin.py
pricing/apps.py
pricing/static/css/pricing/mentor_ds.css
pricing/templates/pricing/_common.html
pricing/templates/pricing/mentor_ds.html
pricing/templatetags/__init__.py
pricing/templatetags/pricing_tags.py
django_mentor_components-0.1.1.dist-info/LICENSE
django_mentor_components-0.1.1.dist-info/METADATA
django_mentor_components-0.1.1.dist-info/WHEEL
django_mentor_components-0.1.1.dist-info/top_level.txt
django_mentor_components-0.1.1.dist-info/RECORD
